{
  "session_id": "session_003",
  "collection_time": "2025-11-06T00:13:51.073895",
  "pose_duration": 15,
  "total_poses": 3,
  "results": [
    {
      "pose": "flat_hand",
      "samples": 279,
      "file": "data/camera_recordings/session_003/flat_hand/camera_data.json"
    },
    {
      "pose": "fist",
      "samples": 359,
      "file": "data/camera_recordings/session_003/fist/camera_data.json"
    },
    {
      "pose": "grab",
      "samples": 370,
      "file": "data/camera_recordings/session_003/grab/camera_data.json"
    }
  ]
}